py2pyaddpy/__init__.py
py2pyaddpy-0.0.2.dist-info/LICENSE.txt
py2pyaddpy-0.0.2.dist-info/METADATA
py2pyaddpy-0.0.2.dist-info/WHEEL
py2pyaddpy-0.0.2.dist-info/top_level.txt
py2pyaddpy-0.0.2.dist-info/RECORD
