Metadata-Version: 2.1
Name: py2pyaddpy
Version: 0.0.2
Summary: adding number
Home-page: UNKNOWN
Author: Ajay Prajapati
Author-email: kpajay.17@gmail.com
License: UNKNOWN
Platform: UNKNOWN
Classifier: Programming Language :: Python :: 3
Classifier: License :: OSI Approved :: MIT License
Classifier: Operating System :: OS Independent
